{
    "player1": "saguie",
    "player2": "AI",
    "opponent_xp": "普通",
    "timestamp": "2025-05-10 23:18:50",
    "first_player": "saguie",
    "moves": [
        [
            5,
            3
        ],
        [
            5,
            2
        ],
        [
            5,
            4
        ],
        [
            5,
            5
        ],
        [
            4,
            5
        ],
        [
            4,
            3
        ],
        [
            3,
            3
        ],
        [
            4,
            2
        ],
        [
            4,
            4
        ],
        [
            3,
            4
        ],
        [
            3,
            5
        ],
        [
            2,
            5
        ]
    ],
    "result": 2
}